rsvp/__about__.py
rsvp/__init__.py
rsvp/core.py
rsvp/py.typed
rsvp-0.1.3.dist-info/licenses/LICENSE
rsvp-0.1.3.dist-info/WHEEL
rsvp-0.1.3.dist-info/METADATA
rsvp-0.1.3.dist-info/RECORD
