Metadata-Version: 2.4
Name: rsvp
Version: 0.1.3
Summary: RSVP is a asynchronous Python framework.
Author-email: tom65536 <peregrinus@planet.ms>
Requires-Python: >=3.11
License-Expression: MIT
Classifier: Development Status :: 3 - Alpha
Classifier: Framework :: AsyncIO
Classifier: Framework :: Pydantic :: 2
Classifier: Framework :: aiohttp
Classifier: Intended Audience :: Developers
Classifier: Programming Language :: Python :: 3.11
Classifier: Programming Language :: Python :: 3.12
Classifier: Programming Language :: Python :: 3.13
Classifier: Topic :: System :: Distributed Computing
Classifier: Typing :: Typed
License-File: LICENSE
Requires-Dist: pytest>=8.4,<9.0 ; extra == "test"
Requires-Dist: pytest-cov>=6.2,<7.0 ; extra == "test"
Requires-Dist: pytest-asyncio>=1.1,<2.0 ; extra == "test"
Requires-Dist: pyright>=1.1.14,<2.0 ; extra == "type"
Project-URL: Home, https://github.com/tom65536/rsvp
Provides-Extra: test
Provides-Extra: type
